jinja_datatables/__init__.py
jinja_datatables/datatable_classes.py
jinja_datatables/jinja_extensions/__init__.py
jinja_datatables/jinja_extensions/datatableext.py
jinja_datatables/static_assets/html/from_ajax.html
jinja_datatables/static_assets/html/from_html.html
jinja_datatables/static_assets/html/from_js_array.html
jinja_datatables/static_assets/js/table.js
jinja_datatables-0.0.8.dist-info/LICENSE
jinja_datatables-0.0.8.dist-info/METADATA
jinja_datatables-0.0.8.dist-info/WHEEL
jinja_datatables-0.0.8.dist-info/top_level.txt
jinja_datatables-0.0.8.dist-info/RECORD
