Metadata-Version: 2.1
Name: jinja-datatables
Version: 0.0.8
Summary: Python library that helps create searchable, custom filterable datatables
Home-page: https://github.com/theheuman/jinja-datatables
Author: TheHeuman
Author-email: jacob.heuman@gmail.com
License: MIT
Platform: UNKNOWN
Classifier: License :: OSI Approved :: MIT License
Classifier: Programming Language :: Python
Classifier: Programming Language :: Python :: 3
Requires-Dist: Jinja2
